odoo/addons/partner_address_format_domestic/README.rst
odoo/addons/partner_address_format_domestic/__init__.py
odoo/addons/partner_address_format_domestic/__manifest__.py
odoo/addons/partner_address_format_domestic/i18n/it.po
odoo/addons/partner_address_format_domestic/i18n/partner_address_format_domestic.pot
odoo/addons/partner_address_format_domestic/models/__init__.py
odoo/addons/partner_address_format_domestic/models/res_country.py
odoo/addons/partner_address_format_domestic/models/res_partner.py
odoo/addons/partner_address_format_domestic/readme/CONFIGURE.rst
odoo/addons/partner_address_format_domestic/readme/CONTEXT.rst
odoo/addons/partner_address_format_domestic/readme/CONTRIBUTORS.rst
odoo/addons/partner_address_format_domestic/readme/DESCRIPTION.rst
odoo/addons/partner_address_format_domestic/static/description/icon.png
odoo/addons/partner_address_format_domestic/static/description/index.html
odoo/addons/partner_address_format_domestic/tests/__init__.py
odoo/addons/partner_address_format_domestic/tests/test_partner_address_format_domestic.py
odoo/addons/partner_address_format_domestic/views/res_country_views.xml
odoo_addon_partner_address_format_domestic-16.0.1.0.0.4.dist-info/METADATA
odoo_addon_partner_address_format_domestic-16.0.1.0.0.4.dist-info/WHEEL
odoo_addon_partner_address_format_domestic-16.0.1.0.0.4.dist-info/top_level.txt
odoo_addon_partner_address_format_domestic-16.0.1.0.0.4.dist-info/RECORD
